fuckcode/__init__.py
fuckcode/__main__.py
fuckcode/compiler.py
fuckcode/translate.py
fuckcode-0.0.21.dist-info/LICENSE
fuckcode-0.0.21.dist-info/METADATA
fuckcode-0.0.21.dist-info/WHEEL
fuckcode-0.0.21.dist-info/entry_points.txt
fuckcode-0.0.21.dist-info/RECORD
